markmodule/__init__.py
markmodule/class_source.py
markmodule/generate_pyi.py
markmodule/import_string.py
markmodule/md_importer.py
markmodule/string_loader.py
markmodule-0.3.0.dist-info/LICENSE
markmodule-0.3.0.dist-info/METADATA
markmodule-0.3.0.dist-info/WHEEL
markmodule-0.3.0.dist-info/RECORD
